<?xml version="1.0" encoding="utf-8"?>
<tt xmlns="http://www.w3.org/ns/ttml" xmlns:ttp="http://www.w3.org/ns/ttml#parameter" ttp:timeBase="media" xmlns:tts="http://www.w3.org/ns/ttml#style" xml:lang="en" xmlns:ttm="http://www.w3.org/ns/ttml#metadata">
  <head>
    <metadata>
      <ttm:title></ttm:title>
    </metadata>
    <styling>
      <style id="s0" tts:backgroundColor="black" tts:fontStyle="normal" tts:fontSize="16" tts:fontFamily="sansSerif" tts:color="white" />
    </styling>
  </head>
  <body style="s0">
    <div>
      <p begin="9.766s" id="p0" end="14.366s">Narratrice: Zoom Text Express est un logiciel d’agrandissement.</p>
      <p begin="14.366s" id="p1" end="17.099s">Le zoom peut concerner soit l’écran entier,</p>
      <p begin="17.1s" id="p2" end="20.633s">soit une petite fenêtre, soit une grande fenêtre.</p>
      <p begin="20.633s" id="p3" end="23.666s">Il peut être agrandi jusqu’à deux fois.</p>
      <p begin="23.666s" id="p4" end="36.099s"></p>
      <p begin="36.1s" id="p5" end="38.7s">Les contrastes peuvent être modifiés</p>
      <p begin="38.7s" id="p6" end="42.133s">ainsi que la couleur du pointeur et du curseur.</p>
    </div>
  </body>
</tt>